<annotation>
	<folder>train</folder>
	<filename>131.jpg</filename>
	<path>D:\GitHub\logo_detection\data\images\train\131.jpg</path>
	<source>
		<database>Unknown</database>
	</source>
	<size>
		<width>800</width>
		<height>600</height>
		<depth>3</depth>
	</size>
	<segmented>0</segmented>
	<object>
		<name>Apple</name>
		<pose>Unspecified</pose>
		<truncated>0</truncated>
		<difficult>0</difficult>
		<bndbox>
			<xmin>340</xmin>
			<ymin>474</ymin>
			<xmax>443</xmax>
			<ymax>517</ymax>
		</bndbox>
	</object>
	<object>
		<name>Apple</name>
		<pose>Unspecified</pose>
		<truncated>0</truncated>
		<difficult>0</difficult>
		<bndbox>
			<xmin>311</xmin>
			<ymin>272</ymin>
			<xmax>393</xmax>
			<ymax>303</ymax>
		</bndbox>
	</object>
	<object>
		<name>Apple</name>
		<pose>Unspecified</pose>
		<truncated>0</truncated>
		<difficult>0</difficult>
		<bndbox>
			<xmin>4</xmin>
			<ymin>175</ymin>
			<xmax>89</xmax>
			<ymax>206</ymax>
		</bndbox>
	</object>
</annotation>
