<annotation>
	<folder>train</folder>
	<filename>627.jpg</filename>
	<path>D:\GitHub\logo_detection\data\images\train\627.jpg</path>
	<source>
		<database>Unknown</database>
	</source>
	<size>
		<width>800</width>
		<height>600</height>
		<depth>3</depth>
	</size>
	<segmented>0</segmented>
	<object>
		<name>Shell</name>
		<pose>Unspecified</pose>
		<truncated>0</truncated>
		<difficult>0</difficult>
		<bndbox>
			<xmin>340</xmin>
			<ymin>203</ymin>
			<xmax>564</xmax>
			<ymax>453</ymax>
		</bndbox>
	</object>
</annotation>
