<annotation>
	<folder>train</folder>
	<filename>878.jpg</filename>
	<path>D:\GitHub\logo_detection\data\images\train\878.jpg</path>
	<source>
		<database>Unknown</database>
	</source>
	<size>
		<width>800</width>
		<height>600</height>
		<depth>3</depth>
	</size>
	<segmented>0</segmented>
	<object>
		<name>Toyota</name>
		<pose>Unspecified</pose>
		<truncated>0</truncated>
		<difficult>0</difficult>
		<bndbox>
			<xmin>475</xmin>
			<ymin>64</ymin>
			<xmax>773</xmax>
			<ymax>234</ymax>
		</bndbox>
	</object>
	<object>
		<name>Toyota</name>
		<pose>Unspecified</pose>
		<truncated>1</truncated>
		<difficult>0</difficult>
		<bndbox>
			<xmin>1</xmin>
			<ymin>93</ymin>
			<xmax>241</xmax>
			<ymax>312</ymax>
		</bndbox>
	</object>
</annotation>
